setup.cfg
setup.py
batch_rename.egg-info/PKG-INFO
batch_rename.egg-info/SOURCES.txt
batch_rename.egg-info/dependency_links.txt
batch_rename.egg-info/requires.txt
batch_rename.egg-info/top_level.txt
batch_renamer_cli/__init__.py
batch_renamer_cli/color.py
batch_renamer_cli/sort_by_name.py
scripts/batch-rename