Metadata-Version: 1.1
Name: batch-rename
Version: 1.0.6
Summary: An easy to use python script for quickly renaming multiple files ending with incrementing numbers.
Home-page: https://github.com/darko3/batch-renamer
Author: Girish Oemrawsingh
Author-email: girish.oemrawsingh@protonmail.com
License: MIT
Download-URL: https://github.com/darko3/batch-renamer/archive/1.0.6.tar.gz
Keywords: batch-renamer,files,python
Platform: UNKNOWN
